<?xml version="1.0" encoding="UTF-8"?>
<sbml xmlns="http://www.sbml.org/sbml/level2/version4" level="2" version="4">
  <model id="E2_PBPK_GSMN_v6_3_xpn">
    <listOfUnitDefinitions>
      <unitDefinition id="substance">
        <listOfUnits>
          <unit kind="item"/>
        </listOfUnits>
      </unitDefinition>
    </listOfUnitDefinitions>
    <listOfCompartments>
      <compartment id="compartment" spatialDimensions="0"/>
    </listOfCompartments>
    <listOfSpecies>
      <species id="E2_lung" compartment="compartment" initialAmount="0" hasOnlySubstanceUnits="true"/>
      <species id="E2_heart" compartment="compartment" initialAmount="0" hasOnlySubstanceUnits="true"/>
      <species id="E2_bone" compartment="compartment" initialAmount="0" hasOnlySubstanceUnits="true"/>
      <species id="E2_ROB" compartment="compartment" initialAmount="0" hasOnlySubstanceUnits="true"/>
      <species id="E2_thymus" compartment="compartment" initialAmount="0" hasOnlySubstanceUnits="true"/>
      <species id="E2_kidney" compartment="compartment" initialAmount="0" hasOnlySubstanceUnits="true"/>
      <species id="E2_arterial" compartment="compartment" initialAmount="0" hasOnlySubstanceUnits="true"/>
      <species id="E2_venous" compartment="compartment" initialAmount="0" hasOnlySubstanceUnits="true"/>
      <species id="Weight" compartment="compartment" initialAmount="0" hasOnlySubstanceUnits="true"/>
      <species id="Height" compartment="compartment" initialAmount="0" hasOnlySubstanceUnits="true"/>
      <species id="Age" compartment="compartment" initialAmount="0" hasOnlySubstanceUnits="true"/>
      <species id="BSA" compartment="compartment" initialAmount="0" hasOnlySubstanceUnits="true"/>
      <species id="BMI" compartment="compartment" initialAmount="0" hasOnlySubstanceUnits="true"/>
      <species id="volume_adipose" compartment="compartment" initialAmount="0" hasOnlySubstanceUnits="true"/>
      <species id="volume_lung" compartment="compartment" initialAmount="0" hasOnlySubstanceUnits="true"/>
      <species id="volume_heart" compartment="compartment" initialAmount="0" hasOnlySubstanceUnits="true"/>
      <species id="volume_bone" compartment="compartment" initialAmount="0" hasOnlySubstanceUnits="true"/>
      <species id="volume_ROB" compartment="compartment" initialAmount="0" hasOnlySubstanceUnits="true"/>
      <species id="volume_thymus" compartment="compartment" initialAmount="0" hasOnlySubstanceUnits="true"/>
      <species id="volume_kidney" compartment="compartment" initialAmount="0" hasOnlySubstanceUnits="true"/>
      <species id="volume_muscle" compartment="compartment" initialAmount="0" hasOnlySubstanceUnits="true"/>
      <species id="volume_muscle_cells" compartment="compartment" initialAmount="0" hasOnlySubstanceUnits="true"/>
      <species id="volume_gonads" compartment="compartment" initialAmount="0" hasOnlySubstanceUnits="true"/>
      <species id="volume_brain" compartment="compartment" initialAmount="0" hasOnlySubstanceUnits="true"/>
      <species id="volume_skin" compartment="compartment" initialAmount="0" hasOnlySubstanceUnits="true"/>
      <species id="volume_blood_arterial" compartment="compartment" initialAmount="0" hasOnlySubstanceUnits="true"/>
      <species id="volume_blood_venous" compartment="compartment" initialAmount="0" hasOnlySubstanceUnits="true"/>
      <species id="volume_stomach" compartment="compartment" initialAmount="0" hasOnlySubstanceUnits="true"/>
      <species id="volume_intestine" compartment="compartment" initialAmount="0" hasOnlySubstanceUnits="true"/>
      <species id="volume_spleen" compartment="compartment" initialAmount="0" hasOnlySubstanceUnits="true"/>
      <species id="volume_pancreas" compartment="compartment" initialAmount="0" hasOnlySubstanceUnits="true"/>
      <species id="volume_liver" compartment="compartment" initialAmount="0" hasOnlySubstanceUnits="true"/>
      <species id="volume_liver_blood" compartment="compartment" initialAmount="0" hasOnlySubstanceUnits="true"/>
      <species id="bloodflow_adipose" compartment="compartment" initialAmount="0" hasOnlySubstanceUnits="true"/>
      <species id="bloodflow_skin" compartment="compartment" initialAmount="0" hasOnlySubstanceUnits="true"/>
      <species id="bloodflow_brain" compartment="compartment" initialAmount="0" hasOnlySubstanceUnits="true"/>
      <species id="bloodflow_gonads" compartment="compartment" initialAmount="0" hasOnlySubstanceUnits="true"/>
      <species id="bloodflow_muscle" compartment="compartment" initialAmount="0" hasOnlySubstanceUnits="true"/>
      <species id="bloodflow_pancreas" compartment="compartment" initialAmount="0" hasOnlySubstanceUnits="true"/>
      <species id="bloodflow_spleen" compartment="compartment" initialAmount="0" hasOnlySubstanceUnits="true"/>
      <species id="bloodflow_intestine" compartment="compartment" initialAmount="0" hasOnlySubstanceUnits="true"/>
      <species id="bloodflow_stomach" compartment="compartment" initialAmount="0" hasOnlySubstanceUnits="true"/>
      <species id="bloodflow_kidney" compartment="compartment" initialAmount="0" hasOnlySubstanceUnits="true"/>
      <species id="bloodflow_ROB" compartment="compartment" initialAmount="0" hasOnlySubstanceUnits="true"/>
      <species id="bloodflow_bone" compartment="compartment" initialAmount="0" hasOnlySubstanceUnits="true"/>
      <species id="bloodflow_heart" compartment="compartment" initialAmount="0" hasOnlySubstanceUnits="true"/>
      <species id="bloodflow_lung" compartment="compartment" initialAmount="0" hasOnlySubstanceUnits="true"/>
      <species id="bloodflow_liver_arterial" compartment="compartment" initialAmount="0" hasOnlySubstanceUnits="true"/>
      <species id="bloodflow_thymus" compartment="compartment" initialAmount="0" hasOnlySubstanceUnits="true"/>
      <species id="bloodflow_liver_venous" compartment="compartment" initialAmount="0" hasOnlySubstanceUnits="true"/>
      <species id="Dose_IV_bolus" compartment="compartment" initialAmount="0" hasOnlySubstanceUnits="true"/>
      <species id="E2_adipose" compartment="compartment" initialAmount="0" hasOnlySubstanceUnits="true"/>
      <species id="E2_muscle" compartment="compartment" initialAmount="0" hasOnlySubstanceUnits="true"/>
      <species id="E2_gonads" compartment="compartment" initialAmount="0" hasOnlySubstanceUnits="true"/>
      <species id="E2_brain" compartment="compartment" initialAmount="0" hasOnlySubstanceUnits="true"/>
      <species id="E2_skin" compartment="compartment" initialAmount="0" hasOnlySubstanceUnits="true"/>
      <species id="E2_liver_blood" compartment="compartment" initialAmount="0" hasOnlySubstanceUnits="true"/>
      <species id="E2_liver" compartment="compartment" initialAmount="0" hasOnlySubstanceUnits="true"/>
      <species id="E2_stomach" compartment="compartment" initialAmount="0" hasOnlySubstanceUnits="true"/>
      <species id="E2_intestine" compartment="compartment" initialAmount="0" hasOnlySubstanceUnits="true"/>
      <species id="E2_spleen" compartment="compartment" initialAmount="0" hasOnlySubstanceUnits="true"/>
      <species id="E2_pancreas" compartment="compartment" initialAmount="0" hasOnlySubstanceUnits="true"/>
      <species id="ER_liver" compartment="compartment" initialAmount="0" hasOnlySubstanceUnits="true"/>
      <species id="E2_ER_liver" compartment="compartment" initialAmount="0" hasOnlySubstanceUnits="true"/>
      <species id="SHBG_venous" compartment="compartment" initialAmount="0" hasOnlySubstanceUnits="true"/>
      <species id="E2_SHBG_venous" compartment="compartment" initialAmount="0" hasOnlySubstanceUnits="true"/>
      <species id="albumin_venous" compartment="compartment" initialAmount="0" hasOnlySubstanceUnits="true"/>
      <species id="E2_albumin_venous" compartment="compartment" initialAmount="0" hasOnlySubstanceUnits="true"/>
      <species id="SHBG_arterial" compartment="compartment" initialAmount="0" hasOnlySubstanceUnits="true"/>
      <species id="E2_SHBG_arterial" compartment="compartment" initialAmount="0" hasOnlySubstanceUnits="true"/>
      <species id="albumin_arterial" compartment="compartment" initialAmount="0" hasOnlySubstanceUnits="true"/>
      <species id="E2_albumin_arterial" compartment="compartment" initialAmount="0" hasOnlySubstanceUnits="true"/>
      <species id="ln_height" compartment="compartment" initialAmount="0" hasOnlySubstanceUnits="true"/>
      <species id="Dose_oral" compartment="compartment" initialAmount="0" hasOnlySubstanceUnits="true"/>
      <species id="Urea" compartment="compartment" initialAmount="0" hasOnlySubstanceUnits="true"/>
      <species id="urea_liver_flux" compartment="compartment" initialAmount="0" hasOnlySubstanceUnits="true"/>
      <species id="LIVER_TURNOVER" compartment="compartment" initialAmount="1" hasOnlySubstanceUnits="true"/>
      <species id="Lactate" compartment="compartment" initialAmount="0" hasOnlySubstanceUnits="true"/>
      <species id="Glucose_regeneration" compartment="compartment" initialAmount="0" hasOnlySubstanceUnits="true"/>
      <species id="Glucose_liver_flux" compartment="compartment" initialAmount="0" hasOnlySubstanceUnits="true"/>
      <species id="RBC" compartment="compartment" initialAmount="0" hasOnlySubstanceUnits="true"/>
      <species id="Lactate_liver_flux" compartment="compartment" initialAmount="0" hasOnlySubstanceUnits="true"/>
      <species id="Glucose" compartment="compartment" initialAmount="0" hasOnlySubstanceUnits="true"/>
      <species id="Hepatocytes" compartment="compartment" initialAmount="0" hasOnlySubstanceUnits="true"/>
      <species id="estradiol_liver_flux" compartment="compartment" initialAmount="0" hasOnlySubstanceUnits="true"/>
      <species id="estradiol_degradation" compartment="compartment" initialAmount="0" hasOnlySubstanceUnits="true"/>
      <species id="CYP3A4mRNA" compartment="compartment" initialAmount="0" hasOnlySubstanceUnits="true"/>
      <species id="degradation" compartment="compartment" initialAmount="0" hasOnlySubstanceUnits="true"/>
      <species id="CYP3A4" compartment="compartment" initialAmount="0" hasOnlySubstanceUnits="true"/>
      <species id="CYP3A4gene" compartment="compartment" initialAmount="0" hasOnlySubstanceUnits="true"/>
      <species id="PXR_act" compartment="compartment" initialAmount="0" hasOnlySubstanceUnits="true"/>
      <species id="PXR" compartment="compartment" initialAmount="0" hasOnlySubstanceUnits="true"/>
      <species id="Phenytoin" compartment="compartment" initialAmount="0" hasOnlySubstanceUnits="true"/>
      <species id="estradiol_2OH_flux" compartment="compartment" initialAmount="0" hasOnlySubstanceUnits="true"/>
      <species id="estrone_SO4_flux" compartment="compartment" initialAmount="0" hasOnlySubstanceUnits="true"/>
      <species id="volume_blood_total" compartment="compartment" initialAmount="0" hasOnlySubstanceUnits="true"/>
      <species id="ER_gonads" compartment="compartment" initialAmount="0" hasOnlySubstanceUnits="true"/>
      <species id="E2_ER_gonads" compartment="compartment" initialAmount="0" hasOnlySubstanceUnits="true"/>
      <species id="volume_gonads_blood" compartment="compartment" initialAmount="0" hasOnlySubstanceUnits="true"/>
      <species id="E2_gonads_blood" compartment="compartment" initialAmount="0" hasOnlySubstanceUnits="true"/>
    </listOfSpecies>
    <listOfReactions>
      <reaction id="lung_arterial" reversible="false">
        <listOfReactants>
          <speciesReference species="E2_lung" stoichiometry="1"/>
        </listOfReactants>
        <listOfProducts>
          <speciesReference species="E2_arterial" stoichiometry="1"/>
        </listOfProducts>
        <listOfModifiers>
          <modifierSpeciesReference species="volume_lung"/>
          <modifierSpeciesReference species="bloodflow_lung"/>
        </listOfModifiers>
        <kineticLaw/>
      </reaction>
      <reaction id="arterial_heart" reversible="false">
        <listOfReactants>
          <speciesReference species="E2_arterial" stoichiometry="1"/>
        </listOfReactants>
        <listOfProducts>
          <speciesReference species="E2_heart" stoichiometry="1"/>
        </listOfProducts>
        <listOfModifiers>
          <modifierSpeciesReference species="bloodflow_heart"/>
          <modifierSpeciesReference species="volume_heart"/>
        </listOfModifiers>
        <kineticLaw/>
      </reaction>
      <reaction id="arterial_bone" reversible="false">
        <listOfReactants>
          <speciesReference species="E2_arterial" stoichiometry="1"/>
        </listOfReactants>
        <listOfProducts>
          <speciesReference species="E2_bone" stoichiometry="1"/>
        </listOfProducts>
        <listOfModifiers>
          <modifierSpeciesReference species="bloodflow_bone"/>
          <modifierSpeciesReference species="volume_bone"/>
        </listOfModifiers>
        <kineticLaw/>
      </reaction>
      <reaction id="arterial_ROB" reversible="false">
        <listOfReactants>
          <speciesReference species="E2_arterial" stoichiometry="1"/>
        </listOfReactants>
        <listOfProducts>
          <speciesReference species="E2_ROB" stoichiometry="1"/>
        </listOfProducts>
        <listOfModifiers>
          <modifierSpeciesReference species="bloodflow_ROB"/>
          <modifierSpeciesReference species="volume_ROB"/>
        </listOfModifiers>
        <kineticLaw/>
      </reaction>
      <reaction id="arterial_thymus" reversible="false">
        <listOfReactants>
          <speciesReference species="E2_arterial" stoichiometry="1"/>
        </listOfReactants>
        <listOfProducts>
          <speciesReference species="E2_thymus" stoichiometry="1"/>
        </listOfProducts>
        <listOfModifiers>
          <modifierSpeciesReference species="bloodflow_thymus"/>
          <modifierSpeciesReference species="volume_thymus"/>
        </listOfModifiers>
        <kineticLaw/>
      </reaction>
      <reaction id="arterial_kidney" reversible="false">
        <listOfReactants>
          <speciesReference species="E2_arterial" stoichiometry="1"/>
        </listOfReactants>
        <listOfProducts>
          <speciesReference species="E2_kidney" stoichiometry="1"/>
        </listOfProducts>
        <listOfModifiers>
          <modifierSpeciesReference species="bloodflow_kidney"/>
          <modifierSpeciesReference species="volume_kidney"/>
        </listOfModifiers>
        <kineticLaw/>
      </reaction>
      <reaction id="venous_lung" reversible="false">
        <listOfReactants>
          <speciesReference species="E2_venous" stoichiometry="1"/>
        </listOfReactants>
        <listOfProducts>
          <speciesReference species="E2_lung" stoichiometry="1"/>
        </listOfProducts>
        <listOfModifiers>
          <modifierSpeciesReference species="volume_lung"/>
          <modifierSpeciesReference species="bloodflow_lung"/>
        </listOfModifiers>
        <kineticLaw/>
      </reaction>
      <reaction id="heart_venous" reversible="false">
        <listOfReactants>
          <speciesReference species="E2_heart" stoichiometry="1"/>
        </listOfReactants>
        <listOfProducts>
          <speciesReference species="E2_venous" stoichiometry="1"/>
        </listOfProducts>
        <listOfModifiers>
          <modifierSpeciesReference species="volume_heart"/>
          <modifierSpeciesReference species="bloodflow_heart"/>
        </listOfModifiers>
        <kineticLaw/>
      </reaction>
      <reaction id="bone_venous" reversible="false">
        <listOfReactants>
          <speciesReference species="E2_bone" stoichiometry="1"/>
        </listOfReactants>
        <listOfProducts>
          <speciesReference species="E2_venous" stoichiometry="1"/>
        </listOfProducts>
        <listOfModifiers>
          <modifierSpeciesReference species="bloodflow_bone"/>
          <modifierSpeciesReference species="volume_bone"/>
        </listOfModifiers>
        <kineticLaw/>
      </reaction>
      <reaction id="ROB_venous" reversible="false">
        <listOfReactants>
          <speciesReference species="E2_ROB" stoichiometry="1"/>
        </listOfReactants>
        <listOfProducts>
          <speciesReference species="E2_venous" stoichiometry="1"/>
        </listOfProducts>
        <listOfModifiers>
          <modifierSpeciesReference species="bloodflow_ROB"/>
          <modifierSpeciesReference species="volume_ROB"/>
        </listOfModifiers>
        <kineticLaw/>
      </reaction>
      <reaction id="thymus_venous" reversible="false">
        <listOfReactants>
          <speciesReference species="E2_thymus" stoichiometry="1"/>
        </listOfReactants>
        <listOfProducts>
          <speciesReference species="E2_venous" stoichiometry="1"/>
        </listOfProducts>
        <listOfModifiers>
          <modifierSpeciesReference species="bloodflow_thymus"/>
          <modifierSpeciesReference species="volume_thymus"/>
        </listOfModifiers>
        <kineticLaw/>
      </reaction>
      <reaction id="kidney_venous" reversible="false">
        <listOfReactants>
          <speciesReference species="E2_kidney" stoichiometry="1"/>
        </listOfReactants>
        <listOfProducts>
          <speciesReference species="E2_venous" stoichiometry="1"/>
        </listOfProducts>
        <listOfModifiers>
          <modifierSpeciesReference species="volume_kidney"/>
          <modifierSpeciesReference species="bloodflow_kidney"/>
        </listOfModifiers>
        <kineticLaw/>
      </reaction>
      <reaction id="Body_mass_index" reversible="false">
        <listOfProducts>
          <speciesReference species="BMI" stoichiometry="1"/>
        </listOfProducts>
        <listOfModifiers>
          <modifierSpeciesReference species="Weight"/>
          <modifierSpeciesReference species="Height"/>
        </listOfModifiers>
        <kineticLaw/>
      </reaction>
      <reaction id="Body_surface_area" reversible="false">
        <listOfProducts>
          <speciesReference species="BSA" stoichiometry="1"/>
        </listOfProducts>
        <listOfModifiers>
          <modifierSpeciesReference species="Weight"/>
          <modifierSpeciesReference species="Height"/>
        </listOfModifiers>
        <kineticLaw/>
      </reaction>
      <reaction id="adipose_vol" reversible="false">
        <listOfProducts>
          <speciesReference species="volume_adipose" stoichiometry="1"/>
        </listOfProducts>
        <listOfModifiers>
          <modifierSpeciesReference species="Weight"/>
          <modifierSpeciesReference species="Age"/>
          <modifierSpeciesReference species="Height"/>
        </listOfModifiers>
        <kineticLaw/>
      </reaction>
      <reaction id="blood_arterial_vol" reversible="false">
        <listOfProducts>
          <speciesReference species="volume_blood_arterial" stoichiometry="1"/>
        </listOfProducts>
        <listOfModifiers>
          <modifierSpeciesReference species="BSA"/>
        </listOfModifiers>
        <kineticLaw/>
      </reaction>
      <reaction id="blood_venous_vol" reversible="false">
        <listOfProducts>
          <speciesReference species="volume_blood_venous" stoichiometry="1"/>
        </listOfProducts>
        <listOfModifiers>
          <modifierSpeciesReference species="BSA"/>
        </listOfModifiers>
        <kineticLaw/>
      </reaction>
      <reaction id="bone_vol" reversible="false">
        <listOfProducts>
          <speciesReference species="volume_bone" stoichiometry="1"/>
        </listOfProducts>
        <listOfModifiers>
          <modifierSpeciesReference species="ln_height"/>
        </listOfModifiers>
        <kineticLaw/>
      </reaction>
      <reaction id="brain_vol" reversible="false">
        <listOfProducts>
          <speciesReference species="volume_brain" stoichiometry="1"/>
        </listOfProducts>
        <listOfModifiers>
          <modifierSpeciesReference species="Age"/>
        </listOfModifiers>
        <kineticLaw/>
      </reaction>
      <reaction id="gonads_vol" reversible="false">
        <listOfProducts>
          <speciesReference species="volume_gonads" stoichiometry="1"/>
        </listOfProducts>
        <listOfModifiers>
          <modifierSpeciesReference species="Age"/>
        </listOfModifiers>
        <kineticLaw/>
      </reaction>
      <reaction id="heart_vol" reversible="false">
        <listOfProducts>
          <speciesReference species="volume_heart" stoichiometry="1"/>
        </listOfProducts>
        <listOfModifiers>
          <modifierSpeciesReference species="ln_height"/>
        </listOfModifiers>
        <kineticLaw/>
      </reaction>
      <reaction id="intestine_vol" reversible="false">
        <listOfProducts>
          <speciesReference species="volume_intestine" stoichiometry="1"/>
        </listOfProducts>
        <listOfModifiers>
          <modifierSpeciesReference species="ln_height"/>
        </listOfModifiers>
        <kineticLaw/>
      </reaction>
      <reaction id="kidney_vol" reversible="false">
        <listOfProducts>
          <speciesReference species="volume_kidney" stoichiometry="1"/>
        </listOfProducts>
        <listOfModifiers>
          <modifierSpeciesReference species="ln_height"/>
        </listOfModifiers>
        <kineticLaw/>
      </reaction>
      <reaction id="liver_vol" reversible="false">
        <listOfProducts>
          <speciesReference species="volume_liver" stoichiometry="1"/>
        </listOfProducts>
        <listOfModifiers>
          <modifierSpeciesReference species="ln_height"/>
        </listOfModifiers>
        <kineticLaw/>
      </reaction>
      <reaction id="liver_blood_vol" reversible="false">
        <listOfProducts>
          <speciesReference species="volume_liver_blood" stoichiometry="1"/>
        </listOfProducts>
        <listOfModifiers>
          <modifierSpeciesReference species="volume_liver"/>
        </listOfModifiers>
        <kineticLaw/>
      </reaction>
      <reaction id="lung_vol" reversible="false">
        <listOfProducts>
          <speciesReference species="volume_lung" stoichiometry="1"/>
        </listOfProducts>
        <listOfModifiers>
          <modifierSpeciesReference species="ln_height"/>
        </listOfModifiers>
        <kineticLaw/>
      </reaction>
      <reaction id="pancreas_vol" reversible="false">
        <listOfProducts>
          <speciesReference species="volume_pancreas" stoichiometry="1"/>
        </listOfProducts>
        <listOfModifiers>
          <modifierSpeciesReference species="ln_height"/>
        </listOfModifiers>
        <kineticLaw/>
      </reaction>
      <reaction id="ROB_vol" reversible="false">
        <listOfProducts>
          <speciesReference species="volume_ROB" stoichiometry="1"/>
        </listOfProducts>
        <listOfModifiers>
          <modifierSpeciesReference species="ln_height"/>
        </listOfModifiers>
        <kineticLaw/>
      </reaction>
      <reaction id="skin_vol" reversible="false">
        <listOfProducts>
          <speciesReference species="volume_skin" stoichiometry="1"/>
        </listOfProducts>
        <listOfModifiers>
          <modifierSpeciesReference species="Weight"/>
          <modifierSpeciesReference species="Height"/>
        </listOfModifiers>
        <kineticLaw/>
      </reaction>
      <reaction id="spleen_vol" reversible="false">
        <listOfProducts>
          <speciesReference species="volume_spleen" stoichiometry="1"/>
        </listOfProducts>
        <listOfModifiers>
          <modifierSpeciesReference species="ln_height"/>
        </listOfModifiers>
        <kineticLaw/>
      </reaction>
      <reaction id="stomach_vol" reversible="false">
        <listOfProducts>
          <speciesReference species="volume_stomach" stoichiometry="1"/>
        </listOfProducts>
        <listOfModifiers>
          <modifierSpeciesReference species="ln_height"/>
        </listOfModifiers>
        <kineticLaw/>
      </reaction>
      <reaction id="thymus_vol" reversible="false">
        <listOfProducts>
          <speciesReference species="volume_thymus" stoichiometry="1"/>
        </listOfProducts>
        <listOfModifiers>
          <modifierSpeciesReference species="Age"/>
        </listOfModifiers>
        <kineticLaw/>
      </reaction>
      <reaction id="muscle_cells_vol" reversible="false">
        <listOfProducts>
          <speciesReference species="volume_muscle_cells" stoichiometry="1"/>
        </listOfProducts>
        <listOfModifiers>
          <modifierSpeciesReference species="Weight"/>
          <modifierSpeciesReference species="volume_stomach"/>
          <modifierSpeciesReference species="volume_spleen"/>
          <modifierSpeciesReference species="volume_ROB"/>
          <modifierSpeciesReference species="volume_pancreas"/>
          <modifierSpeciesReference species="volume_lung"/>
          <modifierSpeciesReference species="volume_bone"/>
          <modifierSpeciesReference species="volume_heart"/>
          <modifierSpeciesReference species="volume_intestine"/>
          <modifierSpeciesReference species="volume_liver"/>
          <modifierSpeciesReference species="volume_kidney"/>
          <modifierSpeciesReference species="volume_thymus"/>
          <modifierSpeciesReference species="volume_blood_venous"/>
          <modifierSpeciesReference species="volume_blood_arterial"/>
          <modifierSpeciesReference species="volume_liver_blood"/>
          <modifierSpeciesReference species="volume_adipose"/>
          <modifierSpeciesReference species="volume_gonads"/>
          <modifierSpeciesReference species="volume_brain"/>
          <modifierSpeciesReference species="volume_skin"/>
          <modifierSpeciesReference species="volume_gonads_blood"/>
        </listOfModifiers>
        <kineticLaw/>
      </reaction>
      <reaction id="adipose_bloodflow" reversible="false">
        <listOfProducts>
          <speciesReference species="bloodflow_adipose" stoichiometry="1"/>
        </listOfProducts>
        <listOfModifiers>
          <modifierSpeciesReference species="volume_adipose"/>
        </listOfModifiers>
        <kineticLaw/>
      </reaction>
      <reaction id="skin_bloodflow" reversible="false">
        <listOfProducts>
          <speciesReference species="bloodflow_skin" stoichiometry="1"/>
        </listOfProducts>
        <listOfModifiers>
          <modifierSpeciesReference species="volume_skin"/>
        </listOfModifiers>
        <kineticLaw/>
      </reaction>
      <reaction id="muscle_bloodflow" reversible="false">
        <listOfProducts>
          <speciesReference species="bloodflow_muscle" stoichiometry="1"/>
        </listOfProducts>
        <listOfModifiers>
          <modifierSpeciesReference species="volume_muscle_cells"/>
        </listOfModifiers>
        <kineticLaw/>
      </reaction>
      <reaction id="gonads_bloodflow" reversible="false">
        <listOfProducts>
          <speciesReference species="bloodflow_gonads" stoichiometry="1"/>
        </listOfProducts>
        <listOfModifiers>
          <modifierSpeciesReference species="volume_gonads"/>
        </listOfModifiers>
        <kineticLaw/>
      </reaction>
      <reaction id="brain_bloodflow" reversible="false">
        <listOfProducts>
          <speciesReference species="bloodflow_brain" stoichiometry="1"/>
        </listOfProducts>
        <listOfModifiers>
          <modifierSpeciesReference species="volume_brain"/>
        </listOfModifiers>
        <kineticLaw/>
      </reaction>
      <reaction id="stomach_bloodflow" reversible="false">
        <listOfProducts>
          <speciesReference species="bloodflow_stomach" stoichiometry="1"/>
        </listOfProducts>
        <listOfModifiers>
          <modifierSpeciesReference species="volume_stomach"/>
        </listOfModifiers>
        <kineticLaw/>
      </reaction>
      <reaction id="spleen_bloodflow" reversible="false">
        <listOfProducts>
          <speciesReference species="bloodflow_spleen" stoichiometry="1"/>
        </listOfProducts>
        <listOfModifiers>
          <modifierSpeciesReference species="volume_spleen"/>
        </listOfModifiers>
        <kineticLaw/>
      </reaction>
      <reaction id="ROB_bloodflow" reversible="false">
        <listOfProducts>
          <speciesReference species="bloodflow_ROB" stoichiometry="1"/>
        </listOfProducts>
        <listOfModifiers>
          <modifierSpeciesReference species="volume_ROB"/>
        </listOfModifiers>
        <kineticLaw/>
      </reaction>
      <reaction id="pancreas_bloodflow" reversible="false">
        <listOfProducts>
          <speciesReference species="bloodflow_pancreas" stoichiometry="1"/>
        </listOfProducts>
        <listOfModifiers>
          <modifierSpeciesReference species="volume_pancreas"/>
        </listOfModifiers>
        <kineticLaw/>
      </reaction>
      <reaction id="lung_bloodflow" reversible="false">
        <listOfProducts>
          <speciesReference species="bloodflow_lung" stoichiometry="1"/>
        </listOfProducts>
        <listOfModifiers>
          <modifierSpeciesReference species="bloodflow_adipose"/>
          <modifierSpeciesReference species="bloodflow_brain"/>
          <modifierSpeciesReference species="bloodflow_gonads"/>
          <modifierSpeciesReference species="bloodflow_muscle"/>
          <modifierSpeciesReference species="bloodflow_skin"/>
          <modifierSpeciesReference species="bloodflow_stomach"/>
          <modifierSpeciesReference species="bloodflow_ROB"/>
          <modifierSpeciesReference species="bloodflow_pancreas"/>
          <modifierSpeciesReference species="bloodflow_bone"/>
          <modifierSpeciesReference species="bloodflow_heart"/>
          <modifierSpeciesReference species="bloodflow_intestine"/>
          <modifierSpeciesReference species="bloodflow_kidney"/>
          <modifierSpeciesReference species="bloodflow_liver_arterial"/>
          <modifierSpeciesReference species="bloodflow_thymus"/>
          <modifierSpeciesReference species="bloodflow_spleen"/>
        </listOfModifiers>
        <kineticLaw/>
      </reaction>
      <reaction id="kidney_bloodflow" reversible="false">
        <listOfProducts>
          <speciesReference species="bloodflow_kidney" stoichiometry="1"/>
        </listOfProducts>
        <listOfModifiers>
          <modifierSpeciesReference species="volume_kidney"/>
        </listOfModifiers>
        <kineticLaw/>
      </reaction>
      <reaction id="intestine_bloodflow" reversible="false">
        <listOfProducts>
          <speciesReference species="bloodflow_intestine" stoichiometry="1"/>
        </listOfProducts>
        <listOfModifiers>
          <modifierSpeciesReference species="volume_intestine"/>
        </listOfModifiers>
        <kineticLaw/>
      </reaction>
      <reaction id="heart_bloodflow" reversible="false">
        <listOfProducts>
          <speciesReference species="bloodflow_heart" stoichiometry="1"/>
        </listOfProducts>
        <listOfModifiers>
          <modifierSpeciesReference species="volume_heart"/>
        </listOfModifiers>
        <kineticLaw/>
      </reaction>
      <reaction id="bone_bloodflow" reversible="false">
        <listOfProducts>
          <speciesReference species="bloodflow_bone" stoichiometry="1"/>
        </listOfProducts>
        <listOfModifiers>
          <modifierSpeciesReference species="volume_bone"/>
        </listOfModifiers>
        <kineticLaw/>
      </reaction>
      <reaction id="liver_bloodflow_arterial" reversible="false">
        <listOfProducts>
          <speciesReference species="bloodflow_liver_arterial" stoichiometry="1"/>
        </listOfProducts>
        <listOfModifiers>
          <modifierSpeciesReference species="volume_liver"/>
        </listOfModifiers>
        <kineticLaw/>
      </reaction>
      <reaction id="thymus_bloodflow" reversible="false">
        <listOfProducts>
          <speciesReference species="bloodflow_thymus" stoichiometry="1"/>
        </listOfProducts>
        <listOfModifiers>
          <modifierSpeciesReference species="volume_thymus"/>
        </listOfModifiers>
        <kineticLaw/>
      </reaction>
      <reaction id="liver_bloodflow_venous" reversible="false">
        <listOfProducts>
          <speciesReference species="bloodflow_liver_venous" stoichiometry="1"/>
        </listOfProducts>
        <listOfModifiers>
          <modifierSpeciesReference species="bloodflow_stomach"/>
          <modifierSpeciesReference species="bloodflow_spleen"/>
          <modifierSpeciesReference species="bloodflow_pancreas"/>
          <modifierSpeciesReference species="bloodflow_intestine"/>
          <modifierSpeciesReference species="bloodflow_liver_arterial"/>
        </listOfModifiers>
        <kineticLaw/>
      </reaction>
      <reaction id="CLEH" reversible="false">
        <listOfReactants>
          <speciesReference species="E2_kidney" stoichiometry="1"/>
        </listOfReactants>
        <kineticLaw/>
      </reaction>
      <reaction id="iv_infusion" reversible="false">
        <listOfProducts>
          <speciesReference species="E2_venous" stoichiometry="1"/>
        </listOfProducts>
      </reaction>
      <reaction id="iv_bolus" reversible="false">
        <listOfReactants>
          <speciesReference species="Dose_IV_bolus" stoichiometry="1"/>
        </listOfReactants>
        <listOfProducts>
          <speciesReference species="E2_venous" stoichiometry="1"/>
        </listOfProducts>
        <kineticLaw/>
      </reaction>
      <reaction id="adipose_venous" reversible="false">
        <listOfReactants>
          <speciesReference species="E2_adipose" stoichiometry="1"/>
        </listOfReactants>
        <listOfProducts>
          <speciesReference species="E2_venous" stoichiometry="1"/>
        </listOfProducts>
        <listOfModifiers>
          <modifierSpeciesReference species="bloodflow_adipose"/>
          <modifierSpeciesReference species="volume_adipose"/>
        </listOfModifiers>
        <kineticLaw/>
      </reaction>
      <reaction id="arterial_adipose" reversible="false">
        <listOfReactants>
          <speciesReference species="E2_arterial" stoichiometry="1"/>
        </listOfReactants>
        <listOfProducts>
          <speciesReference species="E2_adipose" stoichiometry="1"/>
        </listOfProducts>
        <listOfModifiers>
          <modifierSpeciesReference species="bloodflow_adipose"/>
          <modifierSpeciesReference species="volume_adipose"/>
        </listOfModifiers>
        <kineticLaw/>
      </reaction>
      <reaction id="arterial_muscle" reversible="false">
        <listOfReactants>
          <speciesReference species="E2_arterial" stoichiometry="1"/>
        </listOfReactants>
        <listOfProducts>
          <speciesReference species="E2_muscle" stoichiometry="1"/>
        </listOfProducts>
        <listOfModifiers>
          <modifierSpeciesReference species="bloodflow_muscle"/>
          <modifierSpeciesReference species="volume_muscle"/>
        </listOfModifiers>
        <kineticLaw/>
      </reaction>
      <reaction id="muscle_venous" reversible="false">
        <listOfReactants>
          <speciesReference species="E2_muscle" stoichiometry="1"/>
        </listOfReactants>
        <listOfProducts>
          <speciesReference species="E2_venous" stoichiometry="1"/>
        </listOfProducts>
        <listOfModifiers>
          <modifierSpeciesReference species="bloodflow_muscle"/>
          <modifierSpeciesReference species="volume_muscle"/>
        </listOfModifiers>
        <kineticLaw/>
      </reaction>
      <reaction id="arterial_gonads" reversible="false">
        <listOfReactants>
          <speciesReference species="E2_arterial" stoichiometry="1"/>
        </listOfReactants>
        <listOfProducts>
          <speciesReference species="E2_gonads_blood" stoichiometry="1"/>
        </listOfProducts>
        <listOfModifiers>
          <modifierSpeciesReference species="volume_gonads"/>
          <modifierSpeciesReference species="bloodflow_gonads"/>
        </listOfModifiers>
        <kineticLaw/>
      </reaction>
      <reaction id="gonads_venous" reversible="false">
        <listOfReactants>
          <speciesReference species="E2_gonads_blood" stoichiometry="1"/>
        </listOfReactants>
        <listOfProducts>
          <speciesReference species="E2_venous" stoichiometry="1"/>
        </listOfProducts>
        <listOfModifiers>
          <modifierSpeciesReference species="volume_gonads"/>
          <modifierSpeciesReference species="bloodflow_gonads"/>
        </listOfModifiers>
        <kineticLaw/>
      </reaction>
      <reaction id="brain_venous" reversible="false">
        <listOfReactants>
          <speciesReference species="E2_brain" stoichiometry="1"/>
        </listOfReactants>
        <listOfProducts>
          <speciesReference species="E2_venous" stoichiometry="1"/>
        </listOfProducts>
        <listOfModifiers>
          <modifierSpeciesReference species="bloodflow_brain"/>
          <modifierSpeciesReference species="volume_brain"/>
        </listOfModifiers>
        <kineticLaw/>
      </reaction>
      <reaction id="arterial_brain" reversible="false">
        <listOfReactants>
          <speciesReference species="E2_arterial" stoichiometry="1"/>
        </listOfReactants>
        <listOfProducts>
          <speciesReference species="E2_brain" stoichiometry="1"/>
        </listOfProducts>
        <listOfModifiers>
          <modifierSpeciesReference species="bloodflow_brain"/>
          <modifierSpeciesReference species="volume_brain"/>
        </listOfModifiers>
        <kineticLaw/>
      </reaction>
      <reaction id="arterial_skin" reversible="false">
        <listOfReactants>
          <speciesReference species="E2_arterial" stoichiometry="1"/>
        </listOfReactants>
        <listOfProducts>
          <speciesReference species="E2_skin" stoichiometry="1"/>
        </listOfProducts>
        <listOfModifiers>
          <modifierSpeciesReference species="bloodflow_skin"/>
          <modifierSpeciesReference species="volume_skin"/>
        </listOfModifiers>
        <kineticLaw/>
      </reaction>
      <reaction id="skin_venous" reversible="false">
        <listOfReactants>
          <speciesReference species="E2_skin" stoichiometry="1"/>
        </listOfReactants>
        <listOfProducts>
          <speciesReference species="E2_venous" stoichiometry="1"/>
        </listOfProducts>
        <listOfModifiers>
          <modifierSpeciesReference species="bloodflow_skin"/>
          <modifierSpeciesReference species="volume_skin"/>
        </listOfModifiers>
        <kineticLaw/>
      </reaction>
      <reaction id="liverblood_livercells" reversible="false">
        <listOfReactants>
          <speciesReference species="E2_liver_blood" stoichiometry="1"/>
        </listOfReactants>
        <listOfProducts>
          <speciesReference species="E2_liver" stoichiometry="1"/>
        </listOfProducts>
        <kineticLaw/>
      </reaction>
      <reaction id="livercells_liverblood" reversible="false">
        <listOfReactants>
          <speciesReference species="E2_liver" stoichiometry="1"/>
        </listOfReactants>
        <listOfProducts>
          <speciesReference species="E2_liver_blood" stoichiometry="1"/>
        </listOfProducts>
        <kineticLaw/>
      </reaction>
      <reaction id="liver_venous" reversible="false">
        <listOfReactants>
          <speciesReference species="E2_liver_blood" stoichiometry="1"/>
        </listOfReactants>
        <listOfProducts>
          <speciesReference species="E2_venous" stoichiometry="1"/>
        </listOfProducts>
        <listOfModifiers>
          <modifierSpeciesReference species="volume_liver"/>
          <modifierSpeciesReference species="bloodflow_liver_venous"/>
        </listOfModifiers>
        <kineticLaw/>
      </reaction>
      <reaction id="arterial_liver" reversible="false">
        <listOfReactants>
          <speciesReference species="E2_arterial" stoichiometry="1"/>
        </listOfReactants>
        <listOfProducts>
          <speciesReference species="E2_liver_blood" stoichiometry="1"/>
        </listOfProducts>
        <listOfModifiers>
          <modifierSpeciesReference species="bloodflow_liver_arterial"/>
          <modifierSpeciesReference species="volume_liver"/>
        </listOfModifiers>
        <kineticLaw/>
      </reaction>
      <reaction id="arterial_stomach" reversible="false">
        <listOfReactants>
          <speciesReference species="E2_arterial" stoichiometry="1"/>
        </listOfReactants>
        <listOfProducts>
          <speciesReference species="E2_stomach" stoichiometry="1"/>
        </listOfProducts>
        <listOfModifiers>
          <modifierSpeciesReference species="bloodflow_stomach"/>
          <modifierSpeciesReference species="volume_stomach"/>
        </listOfModifiers>
        <kineticLaw/>
      </reaction>
      <reaction id="stomach_liver" reversible="false">
        <listOfReactants>
          <speciesReference species="E2_stomach" stoichiometry="1"/>
        </listOfReactants>
        <listOfProducts>
          <speciesReference species="E2_liver_blood" stoichiometry="1"/>
        </listOfProducts>
        <listOfModifiers>
          <modifierSpeciesReference species="bloodflow_stomach"/>
          <modifierSpeciesReference species="volume_stomach"/>
        </listOfModifiers>
        <kineticLaw/>
      </reaction>
      <reaction id="arterial_intestine" reversible="false">
        <listOfReactants>
          <speciesReference species="E2_arterial" stoichiometry="1"/>
        </listOfReactants>
        <listOfProducts>
          <speciesReference species="E2_intestine" stoichiometry="1"/>
        </listOfProducts>
        <listOfModifiers>
          <modifierSpeciesReference species="volume_intestine"/>
          <modifierSpeciesReference species="bloodflow_intestine"/>
        </listOfModifiers>
        <kineticLaw/>
      </reaction>
      <reaction id="intestine_liver" reversible="false">
        <listOfReactants>
          <speciesReference species="E2_intestine" stoichiometry="1"/>
        </listOfReactants>
        <listOfProducts>
          <speciesReference species="E2_liver_blood" stoichiometry="1"/>
        </listOfProducts>
        <listOfModifiers>
          <modifierSpeciesReference species="volume_intestine"/>
          <modifierSpeciesReference species="bloodflow_intestine"/>
        </listOfModifiers>
        <kineticLaw/>
      </reaction>
      <reaction id="arterial_spleen" reversible="false">
        <listOfReactants>
          <speciesReference species="E2_arterial" stoichiometry="1"/>
        </listOfReactants>
        <listOfProducts>
          <speciesReference species="E2_spleen" stoichiometry="1"/>
        </listOfProducts>
        <listOfModifiers>
          <modifierSpeciesReference species="bloodflow_spleen"/>
          <modifierSpeciesReference species="volume_spleen"/>
        </listOfModifiers>
        <kineticLaw/>
      </reaction>
      <reaction id="spleen_liver" reversible="false">
        <listOfReactants>
          <speciesReference species="E2_spleen" stoichiometry="1"/>
        </listOfReactants>
        <listOfProducts>
          <speciesReference species="E2_liver_blood" stoichiometry="1"/>
        </listOfProducts>
        <listOfModifiers>
          <modifierSpeciesReference species="bloodflow_spleen"/>
          <modifierSpeciesReference species="volume_spleen"/>
        </listOfModifiers>
        <kineticLaw/>
      </reaction>
      <reaction id="arterial_pancreas" reversible="false">
        <listOfReactants>
          <speciesReference species="E2_arterial" stoichiometry="1"/>
        </listOfReactants>
        <listOfProducts>
          <speciesReference species="E2_pancreas" stoichiometry="1"/>
        </listOfProducts>
        <listOfModifiers>
          <modifierSpeciesReference species="volume_pancreas"/>
          <modifierSpeciesReference species="bloodflow_pancreas"/>
        </listOfModifiers>
        <kineticLaw/>
      </reaction>
      <reaction id="pancreas_liver" reversible="false">
        <listOfReactants>
          <speciesReference species="E2_pancreas" stoichiometry="1"/>
        </listOfReactants>
        <listOfProducts>
          <speciesReference species="E2_liver_blood" stoichiometry="1"/>
        </listOfProducts>
        <listOfModifiers>
          <modifierSpeciesReference species="volume_pancreas"/>
          <modifierSpeciesReference species="bloodflow_pancreas"/>
        </listOfModifiers>
        <kineticLaw/>
      </reaction>
      <reaction id="E2_ER_association" reversible="false">
        <listOfReactants>
          <speciesReference species="E2_liver" stoichiometry="1"/>
          <speciesReference species="ER_liver" stoichiometry="1"/>
        </listOfReactants>
        <listOfProducts>
          <speciesReference species="E2_ER_liver" stoichiometry="1"/>
        </listOfProducts>
        <kineticLaw/>
      </reaction>
      <reaction id="E2_ER_disassociation" reversible="false">
        <listOfReactants>
          <speciesReference species="E2_ER_liver" stoichiometry="1"/>
        </listOfReactants>
        <listOfProducts>
          <speciesReference species="ER_liver" stoichiometry="1"/>
          <speciesReference species="E2_liver" stoichiometry="1"/>
        </listOfProducts>
        <kineticLaw/>
      </reaction>
      <reaction id="E2_SHBG_association_venous" reversible="false">
        <listOfReactants>
          <speciesReference species="E2_venous" stoichiometry="1"/>
          <speciesReference species="SHBG_venous" stoichiometry="1"/>
        </listOfReactants>
        <listOfProducts>
          <speciesReference species="E2_SHBG_venous" stoichiometry="1"/>
        </listOfProducts>
        <kineticLaw/>
      </reaction>
      <reaction id="E2_SHBG_disassociation_venous" reversible="false">
        <listOfReactants>
          <speciesReference species="E2_SHBG_venous" stoichiometry="1"/>
        </listOfReactants>
        <listOfProducts>
          <speciesReference species="E2_venous" stoichiometry="1"/>
          <speciesReference species="SHBG_venous" stoichiometry="1"/>
        </listOfProducts>
        <kineticLaw/>
      </reaction>
      <reaction id="E2_albumin_association_venous" reversible="false">
        <listOfReactants>
          <speciesReference species="E2_venous" stoichiometry="1"/>
          <speciesReference species="albumin_venous" stoichiometry="1"/>
        </listOfReactants>
        <listOfProducts>
          <speciesReference species="E2_albumin_venous" stoichiometry="1"/>
        </listOfProducts>
        <kineticLaw/>
      </reaction>
      <reaction id="E2_albumin_disassociation_venous" reversible="false">
        <listOfReactants>
          <speciesReference species="E2_albumin_venous" stoichiometry="1"/>
        </listOfReactants>
        <listOfProducts>
          <speciesReference species="E2_venous" stoichiometry="1"/>
          <speciesReference species="albumin_venous" stoichiometry="1"/>
        </listOfProducts>
        <kineticLaw/>
      </reaction>
      <reaction id="E2_SHBG_association_arterial" reversible="false">
        <listOfReactants>
          <speciesReference species="E2_arterial" stoichiometry="1"/>
          <speciesReference species="SHBG_arterial" stoichiometry="1"/>
        </listOfReactants>
        <listOfProducts>
          <speciesReference species="E2_SHBG_arterial" stoichiometry="1"/>
        </listOfProducts>
        <kineticLaw/>
      </reaction>
      <reaction id="E2_SHBG_disassociation_arterial" reversible="false">
        <listOfReactants>
          <speciesReference species="E2_SHBG_arterial" stoichiometry="1"/>
        </listOfReactants>
        <listOfProducts>
          <speciesReference species="E2_arterial" stoichiometry="1"/>
          <speciesReference species="SHBG_arterial" stoichiometry="1"/>
        </listOfProducts>
        <kineticLaw/>
      </reaction>
      <reaction id="E2_albumin_association_arterial" reversible="false">
        <listOfReactants>
          <speciesReference species="E2_arterial" stoichiometry="1"/>
          <speciesReference species="albumin_arterial" stoichiometry="1"/>
        </listOfReactants>
        <listOfProducts>
          <speciesReference species="E2_albumin_arterial" stoichiometry="1"/>
        </listOfProducts>
        <kineticLaw/>
      </reaction>
      <reaction id="E2_albumin_disassociation_arterial" reversible="false">
        <listOfReactants>
          <speciesReference species="E2_albumin_arterial" stoichiometry="1"/>
        </listOfReactants>
        <listOfProducts>
          <speciesReference species="E2_arterial" stoichiometry="1"/>
          <speciesReference species="albumin_arterial" stoichiometry="1"/>
        </listOfProducts>
        <kineticLaw/>
      </reaction>
      <reaction id="muscle_vol" reversible="false">
        <listOfProducts>
          <speciesReference species="volume_muscle" stoichiometry="1"/>
        </listOfProducts>
      </reaction>
      <reaction id="Biosynthesis" reversible="false">
        <listOfProducts>
          <speciesReference species="E2_gonads" stoichiometry="1"/>
        </listOfProducts>
      </reaction>
      <reaction id="Oral_dose_rate" reversible="false">
        <listOfReactants>
          <speciesReference species="Dose_oral" stoichiometry="1"/>
        </listOfReactants>
        <listOfProducts>
          <speciesReference species="E2_intestine" stoichiometry="1"/>
        </listOfProducts>
        <kineticLaw/>
      </reaction>
      <reaction id="Elimination" reversible="false">
        <listOfReactants>
          <speciesReference species="Dose_oral" stoichiometry="1"/>
        </listOfReactants>
        <kineticLaw/>
      </reaction>
      <reaction id="F5" reversible="false">
        <listOfProducts>
          <speciesReference species="Urea" stoichiometry="1"/>
        </listOfProducts>
        <listOfModifiers>
          <modifierSpeciesReference species="Hepatocytes"/>
          <modifierSpeciesReference species="urea_liver_flux"/>
        </listOfModifiers>
        <kineticLaw/>
      </reaction>
      <reaction id="R_EX_urea_LPAREN_e_RPAREN_" reversible="false">
        <listOfProducts>
          <speciesReference species="urea_liver_flux" stoichiometry="1"/>
        </listOfProducts>
        <listOfModifiers>
          <modifierSpeciesReference species="estradiol_degradation"/>
        </listOfModifiers>
        <kineticLaw/>
      </reaction>
      <reaction id="NET_GLUCOSE_FLUX" reversible="false">
        <listOfProducts>
          <speciesReference species="Glucose" stoichiometry="1"/>
        </listOfProducts>
      </reaction>
      <reaction id="RECON_2" reversible="false">
        <listOfProducts>
          <speciesReference species="Glucose_regeneration" stoichiometry="1"/>
          <speciesReference species="estradiol_degradation" stoichiometry="1"/>
        </listOfProducts>
        <listOfModifiers>
          <modifierSpeciesReference species="LIVER_TURNOVER"/>
          <modifierSpeciesReference species="Lactate"/>
          <modifierSpeciesReference species="E2_liver"/>
        </listOfModifiers>
        <kineticLaw/>
      </reaction>
      <reaction id="R_EX_glc_LPAREN_e_RPAREN_" reversible="false">
        <listOfProducts>
          <speciesReference species="Glucose_liver_flux" stoichiometry="1"/>
        </listOfProducts>
        <listOfModifiers>
          <modifierSpeciesReference species="Glucose_regeneration"/>
        </listOfModifiers>
        <kineticLaw/>
      </reaction>
      <reaction id="F2" reversible="false">
        <listOfReactants>
          <speciesReference species="Glucose" stoichiometry="1"/>
        </listOfReactants>
        <listOfProducts>
          <speciesReference species="Lactate" stoichiometry="1"/>
        </listOfProducts>
        <listOfModifiers>
          <modifierSpeciesReference species="RBC"/>
        </listOfModifiers>
        <kineticLaw/>
      </reaction>
      <reaction id="R_EX_lac_L_LPAREN_e_RPAREN_" reversible="false">
        <listOfProducts>
          <speciesReference species="Lactate_liver_flux" stoichiometry="1"/>
        </listOfProducts>
        <listOfModifiers>
          <modifierSpeciesReference species="Glucose_regeneration"/>
        </listOfModifiers>
        <kineticLaw/>
      </reaction>
      <reaction id="F3" reversible="false">
        <listOfReactants>
          <speciesReference species="Lactate" stoichiometry="1"/>
        </listOfReactants>
        <listOfModifiers>
          <modifierSpeciesReference species="Hepatocytes"/>
          <modifierSpeciesReference species="Lactate_liver_flux"/>
        </listOfModifiers>
        <kineticLaw/>
      </reaction>
      <reaction id="F1" reversible="false">
        <listOfProducts>
          <speciesReference species="Glucose" stoichiometry="1"/>
        </listOfProducts>
        <listOfModifiers>
          <modifierSpeciesReference species="Hepatocytes"/>
          <modifierSpeciesReference species="Glucose_liver_flux"/>
        </listOfModifiers>
        <kineticLaw/>
      </reaction>
      <reaction id="R_EX_estradiol_LPAREN_e_RPAREN_" reversible="false">
        <listOfProducts>
          <speciesReference species="estradiol_liver_flux" stoichiometry="1"/>
        </listOfProducts>
        <listOfModifiers>
          <modifierSpeciesReference species="estradiol_degradation"/>
        </listOfModifiers>
        <kineticLaw/>
      </reaction>
      <reaction id="F4" reversible="false">
        <listOfReactants>
          <speciesReference species="E2_liver" stoichiometry="1"/>
        </listOfReactants>
        <listOfModifiers>
          <modifierSpeciesReference species="estradiol_liver_flux"/>
          <modifierSpeciesReference species="Hepatocytes"/>
        </listOfModifiers>
        <kineticLaw/>
      </reaction>
      <reaction id="CYP3A4mRNA_degradation" reversible="false">
        <listOfReactants>
          <speciesReference species="CYP3A4mRNA" stoichiometry="1"/>
        </listOfReactants>
        <listOfProducts>
          <speciesReference species="degradation" stoichiometry="1"/>
        </listOfProducts>
        <kineticLaw/>
      </reaction>
      <reaction id="CYP3A4_degradation" reversible="false">
        <listOfReactants>
          <speciesReference species="CYP3A4" stoichiometry="1"/>
        </listOfReactants>
        <listOfProducts>
          <speciesReference species="degradation" stoichiometry="1"/>
        </listOfProducts>
        <kineticLaw/>
      </reaction>
      <reaction id="CYP3A4_translation" reversible="false">
        <listOfProducts>
          <speciesReference species="CYP3A4" stoichiometry="1"/>
        </listOfProducts>
        <listOfModifiers>
          <modifierSpeciesReference species="CYP3A4mRNA"/>
        </listOfModifiers>
        <kineticLaw/>
      </reaction>
      <reaction id="CYP3A4_transcription_basal" reversible="false">
        <listOfProducts>
          <speciesReference species="CYP3A4mRNA" stoichiometry="1"/>
        </listOfProducts>
        <listOfModifiers>
          <modifierSpeciesReference species="CYP3A4gene"/>
        </listOfModifiers>
        <kineticLaw/>
      </reaction>
      <reaction id="CYP3A4_transcription_PXR" reversible="false">
        <listOfProducts>
          <speciesReference species="CYP3A4mRNA" stoichiometry="1"/>
        </listOfProducts>
        <listOfModifiers>
          <modifierSpeciesReference species="CYP3A4gene"/>
          <modifierSpeciesReference species="PXR_act"/>
        </listOfModifiers>
        <kineticLaw/>
      </reaction>
      <reaction id="PXR_activation" reversible="false">
        <listOfReactants>
          <speciesReference species="PXR" stoichiometry="1"/>
          <speciesReference species="Phenytoin" stoichiometry="1"/>
        </listOfReactants>
        <listOfProducts>
          <speciesReference species="PXR_act" stoichiometry="1"/>
        </listOfProducts>
        <kineticLaw/>
      </reaction>
      <reaction id="PXR_deactivation" reversible="false">
        <listOfReactants>
          <speciesReference species="PXR_act" stoichiometry="1"/>
        </listOfReactants>
        <listOfProducts>
          <speciesReference species="PXR" stoichiometry="1"/>
          <speciesReference species="Phenytoin" stoichiometry="1"/>
        </listOfProducts>
        <kineticLaw/>
      </reaction>
      <reaction id="R_RE3013C" reversible="false">
        <listOfProducts>
          <speciesReference species="estradiol_2OH_flux" stoichiometry="1"/>
        </listOfProducts>
        <listOfModifiers>
          <modifierSpeciesReference species="estradiol_degradation"/>
        </listOfModifiers>
        <kineticLaw/>
      </reaction>
      <reaction id="R_ESTSULT" reversible="false">
        <listOfProducts>
          <speciesReference species="estrone_SO4_flux" stoichiometry="1"/>
        </listOfProducts>
        <listOfModifiers>
          <modifierSpeciesReference species="estradiol_degradation"/>
        </listOfModifiers>
        <kineticLaw/>
      </reaction>
      <reaction id="Phenytoin_degradation" reversible="false">
        <listOfReactants>
          <speciesReference species="Phenytoin" stoichiometry="1"/>
        </listOfReactants>
        <kineticLaw/>
      </reaction>
      <reaction id="F6" reversible="false">
        <listOfReactants>
          <speciesReference species="Urea" stoichiometry="1"/>
        </listOfReactants>
        <kineticLaw/>
      </reaction>
      <reaction id="Hepatocyte_number" reversible="false">
        <listOfProducts>
          <speciesReference species="Hepatocytes" stoichiometry="1"/>
        </listOfProducts>
        <listOfModifiers>
          <modifierSpeciesReference species="volume_liver"/>
          <modifierSpeciesReference species="volume_blood_total"/>
        </listOfModifiers>
        <kineticLaw/>
      </reaction>
      <reaction id="blood_total_vol" reversible="false">
        <listOfProducts>
          <speciesReference species="volume_blood_total" stoichiometry="1"/>
        </listOfProducts>
        <listOfModifiers>
          <modifierSpeciesReference species="BSA"/>
        </listOfModifiers>
        <kineticLaw/>
      </reaction>
      <reaction id="E2_ER_association_gonads" reversible="false">
        <listOfReactants>
          <speciesReference species="E2_gonads" stoichiometry="1"/>
          <speciesReference species="ER_gonads" stoichiometry="1"/>
        </listOfReactants>
        <listOfProducts>
          <speciesReference species="E2_ER_gonads" stoichiometry="1"/>
        </listOfProducts>
        <kineticLaw/>
      </reaction>
      <reaction id="E2_ER_disassociation_gonads" reversible="false">
        <listOfReactants>
          <speciesReference species="E2_ER_gonads" stoichiometry="1"/>
        </listOfReactants>
        <listOfProducts>
          <speciesReference species="E2_gonads" stoichiometry="1"/>
          <speciesReference species="ER_gonads" stoichiometry="1"/>
        </listOfProducts>
        <kineticLaw/>
      </reaction>
      <reaction id="gonad_blood_vol" reversible="false">
        <listOfProducts>
          <speciesReference species="volume_gonads_blood" stoichiometry="1"/>
        </listOfProducts>
        <listOfModifiers>
          <modifierSpeciesReference species="volume_gonads"/>
        </listOfModifiers>
        <kineticLaw/>
      </reaction>
      <reaction id="gonadsblood_cells" reversible="false">
        <listOfReactants>
          <speciesReference species="E2_gonads_blood" stoichiometry="1"/>
        </listOfReactants>
        <listOfProducts>
          <speciesReference species="E2_gonads" stoichiometry="1"/>
        </listOfProducts>
        <kineticLaw/>
      </reaction>
      <reaction id="gonadscells_blood" reversible="false">
        <listOfReactants>
          <speciesReference species="E2_gonads" stoichiometry="1"/>
        </listOfReactants>
        <listOfProducts>
          <speciesReference species="E2_gonads_blood" stoichiometry="1"/>
        </listOfProducts>
        <kineticLaw/>
      </reaction>
    </listOfReactions>
  </model>
</sbml>
